[{"topic": "五大營養素中，不含下列哪一種？", "ans": 3, "options": [{"id": 1, "words": "蛋白質"}, {"id": 2, "words": "醣類"}, {"id": 3, "words": "葉菜類"}, {"id": 4, "words": "礦物質"}]}, {"topic": "三大營養素中，何者應佔一天攝取熱量最高比例？", "ans": 1, "options": [{"id": 1, "words": "醣類"}, {"id": 2, "words": "蛋白質"}, {"id": 3, "words": "脂質"}, {"id": 4, "words": "比例一樣"}]}, {"topic": "下列哪一種食物不含維他命C？", "ans": 4, "options": [{"id": 1, "words": "花椰菜"}, {"id": 2, "words": "苦瓜"}, {"id": 3, "words": "檸檬"}, {"id": 4, "words": "黃豆"}]}, {"topic": "下列哪一個不是選擇加工食品時要注意的事情？", "ans": 2, "options": [{"id": 1, "words": "包裝是否完整"}, {"id": 2, "words": "食品顏色越鮮豔越好"}, {"id": 3, "words": "是否添加防腐劑"}, {"id": 4, "words": "標示是否清楚"}]}, {"topic": "下列哪一個是控制體重的好方法？", "ans": 3, "options": [{"id": 1, "words": "吃完東西馬上運動"}, {"id": 2, "words": "不吃東西只喝水"}, {"id": 3, "words": "適量飲食細嚼慢嚥"}, {"id": 4, "words": "只吃青菜"}]}, {"topic": "下列哪一個行為最健康？", "ans": 4, "options": [{"id": 1, "words": "邊喝珍珠奶茶邊打電動"}, {"id": 2, "words": "不吃不喝直接睡覺"}, {"id": 3, "words": "不吃水果改喝果汁"}, {"id": 4, "words": "與家人一起吃少油少鹽的晚餐"}]}, {"topic": "堅果類是屬於哪一類營養素？", "ans": 4, "options": [{"id": 1, "words": "蛋白質"}, {"id": 2, "words": "維生素"}, {"id": 3, "words": "醣類"}, {"id": 4, "words": "脂肪"}]}, {"topic": "哪一個才是健康的飲食習慣？", "ans": 3, "options": [{"id": 1, "words": "只吃自己想吃的東西"}, {"id": 2, "words": "只喝飲料不喝水"}, {"id": 3, "words": "每一種營養素的食物都吃"}, {"id": 4, "words": "只喝果汁不吃水果"}]}, {"topic": "下列哪一個營養素是牙齒的主要成分？", "ans": 1, "options": [{"id": 1, "words": "鈣質"}, {"id": 2, "words": "蛋白質"}, {"id": 3, "words": "纖維質"}, {"id": 4, "words": "維生素"}]}, {"topic": "下列哪一個不是良好的飲食習慣?", "ans": 4, "options": [{"id": 1, "words": "每天吃豐盛的早餐"}, {"id": 2, "words": "攝取的蔬果以在地當季為主"}, {"id": 3, "words": "飲用適量的乳品"}, {"id": 4, "words": "食用過量的肉類"}]}, {"topic": "下列哪一個較適合當早餐?", "ans": 3, "options": [{"id": 1, "words": "蛋糕"}, {"id": 2, "words": "炸雞腿"}, {"id": 3, "words": "燕麥粥"}, {"id": 4, "words": "珍珠奶茶"}]}, {"topic": "下列何者是速食食品的壞處?", "ans": 4, "options": [{"id": 1, "words": "脂肪含量高"}, {"id": 2, "words": "熱量高"}, {"id": 3, "words": "缺乏營養素"}, {"id": 4, "words": "以上皆是"}]}, {"topic": "兒童每天應該至少攝取幾份蔬菜和幾份水果?", "ans": 3, "options": [{"id": 1, "words": "蔬菜和水果各一份"}, {"id": 2, "words": "蔬菜和水果總共一份"}, {"id": 3, "words": "3份蔬菜和2份水果"}, {"id": 4, "words": "不用吃也沒關係"}]}, {"topic": "下列哪個食物沒有含有豐富的鈣質?", "ans": 2, "options": [{"id": 1, "words": "牛奶"}, {"id": 2, "words": "馬鈴薯"}, {"id": 3, "words": "小魚乾"}, {"id": 4, "words": "豆腐"}]}, {"topic": "下列何者是多喝水的好處?", "ans": 4, "options": [{"id": 1, "words": "幫助食物消化"}, {"id": 2, "words": "促進腸胃蠕動"}, {"id": 3, "words": "調節體溫"}, {"id": 4, "words": "以上皆是"}]}, {"topic": "攝取人工反式脂肪可能會增加罹患心血管疾病的風險。下列何者可能含有反式脂肪?", "ans": 4, "options": [{"id": 1, "words": "甜甜圈"}, {"id": 2, "words": "爆米花"}, {"id": 3, "words": "炸雞塊"}, {"id": 4, "words": "以上皆是"}]}, {"topic": "嚴重缺碘會使孩童的智商明顯低落，因此孩童平時應該攝取足夠的碘。請問下列何者為含碘食物?", "ans": 4, "options": [{"id": 1, "words": "海帶"}, {"id": 2, "words": "紫菜"}, {"id": 3, "words": "沙丁魚"}, {"id": 4, "words": "以上皆是"}]}, {"topic": "為什麼市面上的奶茶(添加奶精)不是早餐的好選項?", "ans": 4, "options": [{"id": 1, "words": "含糖量高"}, {"id": 2, "words": "鈣質含量不高"}, {"id": 3, "words": "脂肪量高"}, {"id": 4, "words": "以上皆是"}]}, {"topic": "下列何者不是全穀雜糧類中的根莖類?", "ans": 3, "options": [{"id": 1, "words": "番薯"}, {"id": 2, "words": "馬鈴薯"}, {"id": 3, "words": "紅蘿蔔"}, {"id": 4, "words": "芋頭"}]}, {"topic": "茄子是個紫色寶石，含有很多維生素，其中有一個維生素可以保護眼睛，在胡蘿蔔裡也找的到，請問是哪一個維生素呢？", "ans": 1, "options": [{"id": 1, "words": "維生素A"}, {"id": 2, "words": "維生素B"}, {"id": 3, "words": "維生素D"}, {"id": 4, "words": "維生素E"}]}, {"topic": "阿呆有偏食的習慣，不喜歡吃茄子和苦瓜，而且總是覺得肉吃越多才會越強壯，請問他的飲食金字塔應該要多補充哪一類？", "ans": 3, "options": [{"id": 1, "words": "魚肉豆蛋類"}, {"id": 2, "words": "五穀根莖類"}, {"id": 3, "words": "蔬菜類"}, {"id": 4, "words": "水果類"}]}, {"topic": "現在外面的食物都含有很多的鹽和油，而這些都與烹調方式有關，請問下列哪一個是不健康的烹調方式？", "ans": 2, "options": [{"id": 1, "words": "清蒸"}, {"id": 2, "words": "糖醋"}, {"id": 3, "words": "汆燙"}, {"id": 4, "words": "涼拌"}]}, {"topic": "六大類中提供必須脂肪酸、協助脂溶性維生素吸收、維持正常生理代謝、調節內分泌系統，是哪一類的主要功能？", "ans": 1, "options": [{"id": 1, "words": "油脂與堅果種子類"}, {"id": 2, "words": "蔬菜類"}, {"id": 3, "words": "水果類"}, {"id": 4, "words": "魚肉豆蛋類"}]}, {"topic": "運動時喝水的時機應該怎麼掌握？", "ans": 4, "options": [{"id": 1, "words": "一直喝不要停"}, {"id": 2, "words": "想喝再喝"}, {"id": 3, "words": "運動完再一次喝"}, {"id": 4, "words": "每10～15分鐘定期補充水分"}]}, {"topic": "美美到早餐店買早餐，請你告訴她哪一個套餐最不健康？", "ans": 1, "options": [{"id": 1, "words": "奶酥吐司+紅茶"}, {"id": 2, "words": "地瓜+牛奶"}, {"id": 3, "words": "全榖吐司+豆漿"}, {"id": 4, "words": "紫米飯糰+水果優格"}]}, {"topic": "請問下列何者不屬於營養標示？", "ans": 4, "options": [{"id": 1, "words": "反式脂肪"}, {"id": 2, "words": "熱量"}, {"id": 3, "words": "鈉"}, {"id": 4, "words": "食品添加物名稱"}]}, {"topic": "媽媽要小明去買鮮奶，請問小明在購買時須注意什麼？", "ans": 4, "options": [{"id": 1, "words": "有效日期"}, {"id": 2, "words": "營養標示"}, {"id": 3, "words": "食品標示"}, {"id": 4, "words": "以上皆是"}]}, {"topic": "六大類食物中的哪一類食物要吃最少？", "ans": 1, "options": [{"id": 1, "words": "油脂與堅果種子類"}, {"id": 2, "words": "豆魚肉蛋類"}, {"id": 3, "words": "全穀根莖類"}, {"id": 4, "words": "水果類"}]}, {"topic": "下列何種營養素無法提供熱量？", "ans": 4, "options": [{"id": 1, "words": "醣類"}, {"id": 2, "words": "蛋白質"}, {"id": 3, "words": "脂質"}, {"id": 4, "words": "礦物質"}]}, {"topic": "阿公有便秘的困擾，為了讓阿公可以順暢排便，你該建議他吃具有什麼菌的食物？", "ans": 3, "options": [{"id": 1, "words": "大腸桿菌"}, {"id": 2, "words": "幽門桿菌"}, {"id": 3, "words": "乳酸菌"}, {"id": 4, "words": "肉毒桿菌"}]}, {"topic": "以下哪個口訣為正確的建議蔬果攝取？", "ans": 1, "options": [{"id": 1, "words": "菜比水果多一點"}, {"id": 2, "words": "菜跟水果一樣多"}, {"id": 3, "words": "水果比菜多一點"}, {"id": 4, "words": "飯比蔬菜多一點"}]}, {"topic": "未精緻穀類(如糙米、胚芽米)應佔全穀雜糧類攝取建議量的比率為多少以上？", "ans": 2, "options": [{"id": 1, "words": "½"}, {"id": 2, "words": "⅓"}, {"id": 3, "words": "¼"}, {"id": 4, "words": "⅕"}]}, {"topic": "每天應該攝取幾杯乳品類呢？", "ans": 2, "options": [{"id": 1, "words": "1杯"}, {"id": 2, "words": "2杯"}, {"id": 3, "words": "3杯"}, {"id": 4, "words": "4杯"}]}, {"topic": "下列食物中，何者不屬於乳品類呢？", "ans": 4, "options": [{"id": 1, "words": "奶粉"}, {"id": 2, "words": "優酪乳"}, {"id": 3, "words": "乳酪"}, {"id": 4, "words": "奶精"}]}, {"topic": "毛豆是屬於六大類食物中的哪一類？", "ans": 3, "options": [{"id": 1, "words": "蔬菜類"}, {"id": 2, "words": "全穀雜糧類"}, {"id": 3, "words": "豆魚蛋肉類"}, {"id": 4, "words": "水果類"}]}, {"topic": "酪梨是屬於六大類食物中的哪一類？", "ans": 4, "options": [{"id": 1, "words": "水果類"}, {"id": 2, "words": "全穀雜糧類"}, {"id": 3, "words": "豆魚蛋肉類"}, {"id": 4, "words": "油脂類"}]}, {"topic": "下列哪種食物為蔬菜類？", "ans": 3, "options": [{"id": 1, "words": "玉米"}, {"id": 2, "words": "稜角"}, {"id": 3, "words": "大番茄"}, {"id": 4, "words": "毛豆"}]}, {"topic": "以下哪個食物不屬於全穀雜糧類？", "ans": 2, "options": [{"id": 1, "words": "紅藜"}, {"id": 2, "words": "黑豆"}, {"id": 3, "words": "鷹嘴豆"}, {"id": 4, "words": "小米"}]}, {"topic": "堅果種子等食物每餐應如何攝取呢？", "ans": 1, "options": [{"id": 1, "words": "一茶匙"}, {"id": 2, "words": "兩茶匙"}, {"id": 3, "words": "三茶匙"}, {"id": 4, "words": "四茶匙"}]}]